gammaionctl/__init__.py
gammaionctl/gammaioncli.py
gammaionctl/gammaionctl.py
gammaionctl_tspspi-0.0.2.dist-info/LICENSE.md
gammaionctl_tspspi-0.0.2.dist-info/METADATA
gammaionctl_tspspi-0.0.2.dist-info/WHEEL
gammaionctl_tspspi-0.0.2.dist-info/entry_points.txt
gammaionctl_tspspi-0.0.2.dist-info/top_level.txt
gammaionctl_tspspi-0.0.2.dist-info/RECORD
