Metadata-Version: 2.1
Name: gammaionctl-tspspi
Version: 0.0.2
Summary: Unofficial Gamma ion pump ethernet control CLI utility and library
Home-page: https://github.com/tspspi/gammacli
Author: Thomas Spielauer
Author-email: pypipackages01@tspi.at
Classifier: Programming Language :: Python :: 3
Classifier: License :: OSI Approved :: BSD License
Classifier: Operating System :: OS Independent
Requires-Python: >=3.6
License-File: LICENSE.md
